django_simple_coupons/__init__.py
django_simple_coupons/actions.py
django_simple_coupons/admin.py
django_simple_coupons/apps.py
django_simple_coupons/helpers.py
django_simple_coupons/models.py
django_simple_coupons/tests.py
django_simple_coupons/validations.py
django_simple_coupons/views.py
django_simple_coupons/migrations/0001_initial.py
django_simple_coupons/migrations/__init__.py
django_simple_coupons/migrations/__pycache__/0001_initial.cpython-36.pyc
django_simple_coupons/migrations/__pycache__/__init__.cpython-36.pyc
django_simple_coupons-0.5.dist-info/LICENSE
django_simple_coupons-0.5.dist-info/METADATA
django_simple_coupons-0.5.dist-info/WHEEL
django_simple_coupons-0.5.dist-info/top_level.txt
django_simple_coupons-0.5.dist-info/RECORD
