Metadata-Version: 2.1
Name: django-simple-coupons
Version: 0.5
Summary: A Django app that makes the use of coupons a simple task!
Home-page: https://github.com/Wolfterro/django-simple-coupons
Author: Wolfgang Almeida
Author-email: wolfgang.almeida@yahoo.com
License: MIT License
Platform: UNKNOWN
Classifier: Environment :: Web Environment
Classifier: Framework :: Django
Classifier: Intended Audience :: Developers
Classifier: License :: OSI Approved :: MIT License
Classifier: Operating System :: OS Independent
Classifier: Programming Language :: Python
Classifier: Programming Language :: Python :: 2.7
Classifier: Programming Language :: Python :: 3.5
Classifier: Programming Language :: Python :: 3.6
Classifier: Topic :: Internet :: WWW/HTTP
Classifier: Topic :: Internet :: WWW/HTTP :: Dynamic Content
